[
    {
        "Name": "Moochie Women's Jutti",
        "Price": "Tk 2,990",
        "Image_links": [
            "https://storage.apex4u.com/4df395f8-4616-4fa3-90dd-3fa92c5fdeb7.jpg",
            "https://storage.apex4u.com/2528dd2c-d469-405d-9108-08496f4c5a80.jpg",
            "https://storage.apex4u.com/2dce17a9-aae6-426c-9e21-f088bff7d29d.jpg",
            "https://storage.apex4u.com/56bc53d1-c422-4c1d-a289-0c6d0ac535ad.jpg"
        ],
        "Link": "https://www.apex4u.com/product/moochie-womens-jutti-61558b18",
        "Description": "Elevate your summer style with our vibrant women's juttis. Featuring colorful thread work and sequin detailing, these shoes add a pop of excitement to any outfit. Perfect for summer outings, they offer both comfort and style, ensuring you step out in confidence wherever you go.",
        "Specifications": {
            "Style": "Pumps",
            "Features": [
                "Colorful thread and sequin work",
                "Raw silk material upper",
                "Pure leather lining and sole"
            ],
            "Materials": [
                "Upper: Raw Silk",
                "Lining: Leather",
                "Sole: Leather"
            ]
        },
        "Company": "Apex",
        "Category": "Jutti",
        "Gender": "Female"
    },
    {
        "Name": "Moochie Women's Jutti",
        "Price": "Tk 2,990",
        "Image_links": [
            "https://storage.apex4u.com/b4ed1ad8-3c52-41ac-9a4f-076edfb73508.jpg",
            "https://storage.apex4u.com/3f4610f8-974c-49f9-a621-cf5b8ce74b36.jpg",
            "https://storage.apex4u.com/19d0b657-1bd7-4b96-8e93-eab742c9c615.jpg",
            "https://storage.apex4u.com/1bc8f329-12e2-48ee-99cd-2270abedda67.jpg"
        ],
        "Link": "https://www.apex4u.com/product/moochie-womens-jutti-61598b17",
        "Description": "Embrace the richness of tradition and the beauty of craftsmanship while making a stylish impact. The attention to detail is apparent in every aspect of these exquisite juttis. The traditional motifs and intricate beadwork capture the essence of timeless beauty. Putting these juttis on, you'll find that the cushioned insole makes sure that every stride is both elegant and comfortable, enabling you to move with grace and ease.",
        "Specifications": {
            "Style": "Pumps",
            "Features": [
                "Premium Raw silk upper.",
                "Intricate bead embellishment.",
                "Comfortable and durable sole.",
                "Elegant and trendy."
            ],
            "Materials": [
                "Upper: Raw Silk",
                "Lining: Leather",
                "Sole: Leather"
            ]
        },
        "Company": "Apex",
        "Category": "Jutti",
        "Gender": "Female"
    },
    {
        "Name": "Moochie Women's Jutti",
        "Price": "Tk 2,990",
        "Image_links": [
            "https://storage.apex4u.com/b9c55b05-3540-4551-9164-e32390c727a8.jpg",
            "https://storage.apex4u.com/8200ddf5-1d39-4dcf-8481-a6cd8d782027.jpg",
            "https://storage.apex4u.com/bab4c199-6f8b-4745-b262-9a27ed20e3eb.jpg",
            "https://storage.apex4u.com/47138ca4-ec6c-4c95-aa77-b978ad8353c8.jpg"
        ],
        "Link": "https://www.apex4u.com/product/moochie-womens-jutti-61598b15",
        "Description": "These exquisite juttis by Moochie are where tradition meets fashion in a harmonious dance of elegance and style. These meticulously crafted juttis are a celebration of heritage and a testament to the enduring allure of artisanal craftsmanship. Pair them with a flowing saree for a touch of classical elegance, or wear them with contemporary fusion attire to create a striking fashion statement that bridges the gap between tradition and modernity.",
        "Specifications": {
            "Style": "Pumps",
            "Features": [
                "Premium Raw Silk upper",
                "Intricate embroidery work.",
                "Comfortable and durable sole.",
                "Fashionable and trendy."
            ],
            "Materials": [
                "Upper: Raw Silk",
                "Lining: Leather",
                "Sole: Leather"
            ]
        },
        "Company": "Apex",
        "Category": "Jutti",
        "Gender": "Female"
    },
    {
        "Name": "Moochie Women's Jutti",
        "Price": "Tk 2,990",
        "Image_links": [
            "https://storage.apex4u.com/0cef3bf5-a037-4168-87c6-b7720f5b3697.jpg",
            "https://storage.apex4u.com/cfdbbd35-3057-4868-8487-25f859431515.jpg",
            "https://storage.apex4u.com/abd52270-7dfe-459d-9cef-73c94cd25a99.jpg",
            "https://storage.apex4u.com/5d963229-ed68-46ae-970a-a22af5fc2d3e.jpg"
        ],
        "Link": "https://www.apex4u.com/product/moochie-womens-jutti-61558b16",
        "Description": "Elevate your summer style with our vibrant women's juttis. Featuring colorful thread work and sequin detailing, these shoes add a pop of excitement to any outfit. Perfect for summer outings, they offer both comfort and style, ensuring you step out in confidence wherever you go.",
        "Specifications": {
            "Style": "Pumps",
            "Features": [
                "Colorful thread and sequin work",
                "Raw silk material upper",
                "Pure leather lining and sole"
            ],
            "Materials": [
                "Upper: Raw Silk",
                "Lining: Leather",
                "Sole: Leather"
            ]
        },
        "Company": "Apex",
        "Category": "Jutti",
        "Gender": "Female"
    },
    {
        "Name": "Moochie Women's Jutti",
        "Price": "Tk 2,990",
        "Image_links": [
            "https://storage.apex4u.com/0cd12cf9-778c-49ca-a471-4dad75652e09.jpg",
            "https://storage.apex4u.com/65ce5405-1990-4cb0-9197-d4cbec0c5d51.jpg",
            "https://storage.apex4u.com/14a8759e-a265-4eb1-b1cb-3c808641c418.jpg",
            "https://storage.apex4u.com/37340de2-06ac-4c7f-80a3-5f8a59bb1e2c.jpg"
        ],
        "Link": "https://www.apex4u.com/product/moochie-womens-jutti-61558b13",
        "Description": "Discover our exquisite Juttis, blending tradition and modern style flawlessly. Adorned with intricate designs and embellishments, each pair is a masterpiece celebrating craftsmanship. Handcrafted with premium leather for comfort and durability, they embody the essence of traditional Mojari. From shimmering bling to enchanting rose gold, our shoes are the perfect gift for any special woman in your life.",
        "Specifications": {
            "Style": "Pumps",
            "Features": [
                "Elegant Embellishment",
                "Crafted with beads and pearl",
                "Raw silk material",
                "Pure leather lining and sole"
            ],
            "Materials": [
                "Upper: Raw Silk",
                "Lining; Leather",
                "Sole: Leather"
            ]
        },
        "Company": "Apex",
        "Category": "Jutti",
        "Gender": "Female"
    },
    {
        "Name": "Moochie Women's Jutti",
        "Price": "Tk 2,990",
        "Image_links": [
            "https://storage.apex4u.com/da809fbf-4b81-434d-b2f5-4a6a4699638a.jpg",
            "https://storage.apex4u.com/96b52723-8ff8-43d5-bd68-fc9aa574c790.jpg",
            "https://storage.apex4u.com/3aab5090-860a-4d06-82f1-f671a6be6ecf.jpg",
            "https://storage.apex4u.com/3aa23b9d-6084-4c8a-8d4d-b1d8446b4da9.jpg"
        ],
        "Link": "https://www.apex4u.com/product/moochie-womens-jutti-61558b12",
        "Description": "Lightweight and breathable, our exclusive juttis boast durability and modern design. Perfect for any occasion, they cater to every style-conscious woman. With a comfort sole and flexible walk, they offer ultimate comfort. Crafted for unbeatable style, they complement varied outfits and suit all weather conditions. From casual college days to elegant evenings, these eye-catching juttis with trendy sequins ensure you stand out for all the right reasons.",
        "Specifications": {
            "Style": "Pumps",
            "Features": [
                "Lightweight and breathable",
                "Pearl and stone work upper",
                "Raw silk material"
            ],
            "Materials": [
                "Upper: Raw Silk",
                "Lining: Leather",
                "Sole: Leather"
            ]
        },
        "Company": "Apex",
        "Category": "Jutti",
        "Gender": "Female"
    },
    {
        "Name": "Moochie Women's Jutti",
        "Price": "Tk 2,990",
        "Image_links": [
            "https://storage.apex4u.com/cc0482c0-0ff8-4c61-a147-d6c2e9b6cfa4.jpg",
            "https://storage.apex4u.com/03ca5688-0edc-45d2-b350-b11a79632873.jpg",
            "https://storage.apex4u.com/cd08c43c-176f-4f97-80fd-b988170f1e29.jpg",
            "https://storage.apex4u.com/f53a61b8-68c4-4b3e-a112-7bbac7de39f6.jpg"
        ],
        "Link": "https://www.apex4u.com/product/moochie-womens-jutti-61538b19",
        "Description": "Step into elegance with our Jutti in warm tan. Its rich color and intricate detailing exude timeless beauty. Delicate embroidery and the melodious sound of ghungroo combine tradition and modernity seamlessly. Crafted for comfort and style, these juttis elevate ethnic ensembles and make a statement at any event. Experience elegance with Ghungroo Sand.",
        "Specifications": {
            "Style": "Pumps",
            "Features": [
                "Pure Leather jutti",
                "Comfortable and stylish",
                "Delicate embroidery upper"
            ],
            "Materials": [
                "Upper: Leather",
                "Lining: Leather",
                "Sole: Leather"
            ]
        },
        "Company": "Apex",
        "Category": "Jutti",
        "Gender": "Female"
    },
    {
        "Name": "Moochie Women's Jutti",
        "Price": "Tk 2,990",
        "Image_links": [
            "https://storage.apex4u.com/5af0d38b-b385-44a4-9232-125123d4d60a.jpg",
            "https://storage.apex4u.com/96fafd57-ca30-4b8f-a40e-9959783e561a.jpg",
            "https://storage.apex4u.com/4ef8e43a-20ac-4410-8e78-f806091fd132.jpg",
            "https://storage.apex4u.com/ae60749f-237c-4a72-906f-d5c2bcd9b8c9.jpg"
        ],
        "Link": "https://www.apex4u.com/product/moochie-womens-jutti-61518b11",
        "Description": "This elegant black women's jutti is made from luxurious embroidered velvet, adorned with intricate zardozi hand embroidery, golden dabka, and cutdana. Mounted on a leather jutti with a pure leather sole and lining, it offers durability and comfort. Its floral-petal pattern exudes glamour, perfect for complementing vibrant traditional attire.",
        "Specifications": {
            "Style": "Pumps",
            "Features": [
                "Zardozi Embroidered",
                "Velvet Suede upper",
                "Pure leather sole and lining"
            ],
            "Materials": [
                "Upper: Velvet Suede",
                "Lining: Leather",
                "Sole: Leather"
            ]
        },
        "Company": "Apex",
        "Category": "Jutti",
        "Gender": "Female"
    },
    {
        "Name": "Moochie Women's Jutti",
        "Price": "Tk 2,990",
        "Image_links": [
            "https://storage.apex4u.com/b7c85e0c-7306-42a7-bc10-5de22e56a7d6.jpg",
            "https://storage.apex4u.com/d07ad0d9-28f8-4f4e-9dbf-1870443fd65d.jpg",
            "https://storage.apex4u.com/e8551a38-ae8c-4133-ac85-67aa9a915813.jpg",
            "https://storage.apex4u.com/703e70aa-e493-4687-a54f-cdf55b6a531a.jpg"
        ],
        "Link": "https://www.apex4u.com/product/moochie-womens-jutti-61598b14",
        "Description": "Introducing our women's jutti, a blend of tradition and elegance. Crafted with raw silk upper, adorned with intricate gota patti and cross stitch work, these shoes exude timeless charm. Perfect for adding a touch of cultural sophistication to any outfit, ensuring you step out in style and grace. Style, these traditional yet elegant shoes with ethnic attire like sarees or lehengas for a cultural celebration or pair them with contemporary outfits for a fusion look that exudes sophistication and grace.",
        "Specifications": {
            "Style": "not mentioned",
            "Features": [
                "Premium raw silk material.",
                "Gota patti and cross stitch work .",
                "",
                "Trendy and stylish.",
                "Breathable leather sole ."
            ],
            "Materials": [
                "Upper: Raw Silk",
                "Lining: Leather",
                "Sole: Leather"
            ]
        },
        "Company": "Apex",
        "Category": "Jutti",
        "Gender": "Female"
    },
    {
        "Name": "Moochie Women's Jutti",
        "Price": "Tk 2,990",
        "Image_links": [
            "https://storage.apex4u.com/1da7194c-0330-4e5f-8342-8f1621877ff1.jpg",
            "https://storage.apex4u.com/0b128bca-8fa7-4ce7-813f-ca0d8476060e.jpg",
            "https://storage.apex4u.com/2fa5fcea-b4e9-40c9-82d5-078b2e99bcab.jpg",
            "https://storage.apex4u.com/f2100842-dbd5-4868-9d78-2ba2b19f9220.jpg",
            "https://storage.apex4u.com/1c5d1c71-1bed-4694-b25d-6028370c0917.jpg",
            "https://storage.apex4u.com/a8a9f439-de80-4592-87a3-77486dc027da.jpg",
            "https://storage.apex4u.com/9e6be73a-7108-407f-b7ba-36bf9bdef42c.jpg",
            "https://storage.apex4u.com/cad26ef6-939a-4a43-97d7-bdff3ed6fb47.jpg",
            "https://storage.apex4u.com/c4207260-646a-4135-9f8c-760e12ec5349.jpg"
        ],
        "Link": "https://www.apex4u.com/product/moochie-womens-jutti-61588a79",
        "Description": "Embrace the richness of tradition and the beauty of craftsmanship while making a stylish impact. The attention to detail is apparent in every aspect of these exquisite juttis. The traditional motifs and intricate beadwork capture the essence of timeless beauty. Putting these juttis on, you'll find that the cushioned insole makes sure that every stride is both elegant and comfortable, enabling you to move with grace and ease.",
        "Specifications": {
            "Style": "Pumps",
            "Features": [],
            "Materials": [
                "Upper : Leather",
                "Sole : Leather"
            ]
        },
        "Company": "Apex",
        "Category": "Jutti",
        "Gender": "Female"
    },
    {
        "Name": "Moochie Women's Jutti",
        "Price": "Tk 2,990",
        "Image_links": [
            "https://storage.apex4u.com/75572a84-47f2-4783-a1ca-346036419bfb.jpg",
            "https://storage.apex4u.com/601eab16-a538-489c-bc74-db334a566a23.jpg",
            "https://storage.apex4u.com/21144b07-126f-4792-abff-b759767f1417.jpg",
            "https://storage.apex4u.com/c6e2cc14-78b0-4cc4-9391-56bfdefd6388.jpg",
            "https://storage.apex4u.com/da40bd50-7da6-4b95-b343-53b5bc215b1f.jpg",
            "https://storage.apex4u.com/783a8546-b350-4e92-a721-6e97a7573dce.jpg",
            "https://storage.apex4u.com/98db74d2-bbd6-43e4-9fd6-9b9c99937184.jpg",
            "https://storage.apex4u.com/4ed44009-36d0-4c66-80e2-d4404043ea71.jpg",
            "https://storage.apex4u.com/1698debd-74fd-4631-a4f1-dc263fc3f535.jpg"
        ],
        "Link": "https://www.apex4u.com/product/moochie-womens-jutti-61558a91",
        "Description": "Embrace the richness of tradition and the beauty of craftsmanship while making a stylish impact. The attention to detail is apparent in every aspect of these exquisite juttis. The traditional motifs and intricate beadwork capture the essence of timeless beauty. Slip into these juttis, and you'll discover a cushioned insole that ensures every step is as comfortable as it is graceful, allowing you to move with ease and elegance.",
        "Specifications": {
            "Style": "Pumps",
            "Features": [
                "Premium leather upper.",
                "Intricate bead embellishment.",
                "Comfortable and durable sole.",
                "Elegant and stylish."
            ],
            "Materials": [
                "Upper : Leather",
                "Sole : Leather"
            ]
        },
        "Company": "Apex",
        "Category": "Jutti",
        "Gender": "Female"
    },
    {
        "Name": "Moochie Women's Jutti",
        "Price": "Tk 2,990",
        "Image_links": [
            "https://storage.apex4u.com/582e9e3c-2347-441b-ac8e-ba16cdb78926.jpg",
            "https://storage.apex4u.com/8ae6dae4-a2c7-4da8-b62b-ef1937935209.jpg",
            "https://storage.apex4u.com/aafc2042-10b1-4558-9221-ab36c28a3a87.jpg",
            "https://storage.apex4u.com/f8c83dd5-3181-4d20-9402-5c9c23372005.jpg",
            "https://storage.apex4u.com/28ea20b3-81a9-435a-8f55-6ec1494bdc5c.jpg",
            "https://storage.apex4u.com/206d93a2-2f8d-4721-9063-59cfe336efdc.jpg",
            "https://storage.apex4u.com/25cf91da-1d7e-4eee-a69a-93d30eb55c14.jpg",
            "https://storage.apex4u.com/818f0338-f4c5-4566-b891-58fdc49ac645.jpg",
            "https://storage.apex4u.com/4fe29ea2-2794-418b-910d-6ac13e650a66.jpg"
        ],
        "Link": "https://www.apex4u.com/product/moochie-womens-jutti-61518a90",
        "Description": "With Moochie Women's Jutti, you'll radiate elegance with a classic fusion of fashion and tradition. These precisely crafted and elaborately detailed juttis combine comfort and sophistication in a seamless fashion. Superior materials guarantee longevity, and the stylish design gives traditional craftsmanship a modern twist. With Moochie Jutti, you can boost your attire to a new level where every step oozes grace and cultural charm and makes a fashion statement.",
        "Specifications": {
            "Style": "Pumps",
            "Features": [
                "Premium leather upper.",
                "Intricate bead embellishment.",
                "Comfortable and durable sole.",
                "Elegant and stylish."
            ],
            "Materials": [
                "Upper : Leather",
                "Sole : Leather"
            ]
        },
        "Company": "Apex",
        "Category": "Jutti",
        "Gender": "Female"
    },
    {
        "Name": "Moochie Women's Jutti",
        "Price": "Tk 2,990",
        "Image_links": [
            "https://storage.apex4u.com/f3e34cf2-1efe-4750-8c5e-b35a505d0b8b.jpg",
            "https://storage.apex4u.com/2f6e1c09-44d5-4fe7-96da-8f9cdb4ba299.jpg",
            "https://storage.apex4u.com/62db0a7c-a7a5-4474-97ee-6f9774514fe7.jpg",
            "https://storage.apex4u.com/ec56618c-c953-4c6b-afb0-470d473bb3aa.jpg",
            "https://storage.apex4u.com/f7e69756-4f7e-4f33-ba9c-b6616c2617c8.jpg",
            "https://storage.apex4u.com/5c2262d4-7cec-4bb3-a7d6-f091259ab094.jpg",
            "https://storage.apex4u.com/2faba888-6d1d-4254-a4f0-a60a357e81d1.jpg",
            "https://storage.apex4u.com/e3b65c53-9a3f-453c-ae9d-22f00a138141.jpg",
            "https://storage.apex4u.com/7a1e61c8-b3cf-4007-bf5e-d72fb3e7c786.jpg"
        ],
        "Link": "https://www.apex4u.com/product/moochie-womens-jutti-61558a80",
        "Description": "These exquisite pair of juttis from Moochie are a work of art. The intricate embroidery and vibrant colors evoke a sense of celebration, making these juttis the perfect choice for weddings, festivals and special occasions. Wear Moochie Women's Jutti to exude elegance and turn heads everywhere you go.",
        "Specifications": {
            "Style": "Pumps",
            "Features": [
                "Premium leather upper.",
                "Intricate bead embellishment.",
                "Comfortable and durable sole.",
                "Trendy and stylish."
            ],
            "Materials": "not mentioned"
        },
        "Company": "Apex",
        "Category": "Jutti",
        "Gender": "Female"
    },
    {
        "Name": "Moochie Women's Jutti",
        "Price": "Tk 2,990",
        "Image_links": [
            "https://storage.apex4u.com/acbee4b1-ea84-4dd3-ad57-1b9a319726b1.jpg",
            "https://storage.apex4u.com/e898906a-d67c-4b00-a60d-095c2f00725c.jpg",
            "https://storage.apex4u.com/db06abbf-18a7-44ba-9d1e-e679300f4a11.jpg",
            "https://storage.apex4u.com/7d2503ac-7915-4726-87a9-5128c41750be.jpg",
            "https://storage.apex4u.com/53ac9ab9-1642-4bc1-84cb-34137622b55e.jpg",
            "https://storage.apex4u.com/a72c6fcf-d7b3-4bed-9d91-9331f30819a1.jpg",
            "https://storage.apex4u.com/8fdab99b-ba85-46d5-bb34-1f78888e357d.jpg",
            "https://storage.apex4u.com/27730f63-8fc5-4095-b2cc-7a4b04e095eb.jpg",
            "https://storage.apex4u.com/57a2a3fb-e52f-4078-a6a9-bc99c69f684a.jpg"
        ],
        "Link": "https://www.apex4u.com/product/moochie-womens-jutti-61558a78",
        "Description": "These exquisite pair of juttis from Moochie are a work of art. The intricate embroidery and vibrant colors evoke a sense of celebration, making these juttis the perfect choice for weddings, festivals, and special occasions. Upgrade your style with these stylish juttis. Wear Moochie Women's Jutti to exude elegance and turn heads everywhere you go.",
        "Specifications": {
            "Style": "Pumps",
            "Features": [],
            "Materials": [
                "Upper : Leather",
                "Sole : Leather"
            ]
        },
        "Company": "Apex",
        "Category": "Jutti",
        "Gender": "Female"
    },
    {
        "Name": "Mocchie Women's Zardosi Jutti",
        "Price": "Tk 2,990",
        "Image_links": [
            "https://storage.apex4u.com/76c06231-c8e5-4369-9137-eae546090217.jpg",
            "https://storage.apex4u.com/53bba768-5eb2-401c-a6ba-986f86055678.jpg",
            "https://storage.apex4u.com/6129d4b3-7453-4e22-8935-b0732b5b1a0e.jpg",
            "https://storage.apex4u.com/5744a0d8-ca67-48a3-b2ae-9a05abfeb3dc.jpg",
            "https://storage.apex4u.com/90543b97-5ab8-41e8-a766-45232b9d68db.jpg",
            "https://storage.apex4u.com/18164251-994b-49bd-9171-28bd0a9984a4.jpg",
            "https://storage.apex4u.com/88212eca-5ff6-4981-90c7-b925d5d6b32b.jpg",
            "https://storage.apex4u.com/47503a42-3b38-42ae-972c-aeb96ed2f470.jpg",
            "https://storage.apex4u.com/1783b654-b090-432e-80d0-777d414413b1.jpg"
        ],
        "Link": "https://www.apex4u.com/product/mocchie-womens-zardosi-jutti-61598a77",
        "Description": "These exquisite juttis by Moochie are where tradition meets fashion in a harmonious dance of elegance and style. These meticulously crafted juttis are a celebration of heritage and a testament to the enduring allure of artisanal craftsmanship. Pair them with a flowing saree for a touch of classical elegance, or wear them with contemporary fusion attire to create a striking fashion statement that bridges the gap between tradition and modernity.",
        "Specifications": {
            "Style": "Pumps",
            "Features": [
                "",
                "Premium leather upper.",
                "Intricate embroidery work.",
                "Comfortable and durable sole.",
                "Fashionable and trendy."
            ],
            "Materials": [
                "Upper : Leather",
                "Sole : Leather"
            ]
        },
        "Company": "Apex",
        "Category": "Jutti",
        "Gender": "Female"
    },
    {
        "Name": "Moochie Women's Zardosi Jutti",
        "Price": "Tk 2,990",
        "Image_links": [
            "https://storage.apex4u.com/33dcd903-f839-45ec-bd2f-8120d7066ee6.jpg",
            "https://storage.apex4u.com/3ef319ab-4b17-44ff-a81a-dba1088a359a.jpg",
            "https://storage.apex4u.com/237974b1-720d-478c-a497-a9dad78ed69a.jpg",
            "https://storage.apex4u.com/596c9f82-22b6-453c-b986-8a8a77a17f91.jpg",
            "https://storage.apex4u.com/095ab3c6-a54e-440d-9b33-1d00e57cdbd5.jpg",
            "https://storage.apex4u.com/bbe7422a-c67f-4b9e-9fd3-2c2aed80d531.jpg",
            "https://storage.apex4u.com/97be47d1-7420-4000-bf22-df6256ce45b1.jpg",
            "https://storage.apex4u.com/1b6105cb-835a-4c98-98c2-ae69db6bb09f.jpg"
        ],
        "Link": "https://www.apex4u.com/product/moochie-womens-zardosi-jutti-61558a77",
        "Description": "These exquisite juttis by Moochie are where tradition meets fashion in a harmonious dance of elegance and style. These meticulously crafted juttis are a celebration of heritage and a testament to the enduring allure of artisanal craftsmanship. Pair them with a flowing saree for a touch of classical elegance, or wear them with contemporary fusion attire to create a striking fashion statement that bridges the gap between tradition and modernity.",
        "Specifications": {
            "Style": "Pumps",
            "Features": [
                "Premium leather upper.",
                "Intricate embroidery.",
                "Comfortable and durable sole."
            ],
            "Materials": [
                "Upper: Leather",
                "Sole: Leather"
            ]
        },
        "Company": "Apex",
        "Category": "Jutti",
        "Gender": "Female"
    },
    {
        "Name": "Moochie Women's Jutti",
        "Price": "Tk 2,990",
        "Image_links": [
            "https://storage.apex4u.com/61558A48_3.jpeg",
            "https://storage.apex4u.com/61558A48_1.jpeg",
            "https://storage.apex4u.com/61558A48_4.jpeg",
            "https://storage.apex4u.com/61558A48_2.jpeg"
        ],
        "Link": "https://www.apex4u.com/product/moochie-womens-roseate-jutti-61558a48",
        "Description": "Moochie Women's Jutti brings a touch of elegance to your ensemble. These exotic pink juttis are adorned with intricate mirror work, adding a hint of glamour to any outfit. Crafted from premium textile material, they offer both style and comfort. These juttis are ideal for every occasion and will definitely add some color and flair to your outfit. With Moochie Women's Jutti, you can easily boost your style and exude refinement.",
        "Specifications": {
            "Style": "Pumps",
            "Features": [
                "High quality textile material mirror work.",
                "Leather sole closed toe design.",
                "Slightly pointed toe box.",
                "Trendy and stylish."
            ],
            "Materials": [
                "Upper: PU",
                "Sole: Rubber"
            ]
        },
        "Company": "Apex",
        "Category": "Jutti",
        "Gender": "Female"
    },
    {
        "Name": "Moochie Women's Jutti",
        "Price": "Tk 2,990",
        "Image_links": [
            "https://storage.apex4u.com/61598A49_1.jpeg",
            "https://storage.apex4u.com/61598A49_3.jpeg",
            "https://storage.apex4u.com/61598A49_2.jpeg",
            "https://storage.apex4u.com/61598A49_4.jpeg"
        ],
        "Link": "https://www.apex4u.com/product/moochie-womens-ocean-blue-jutti-61598a49",
        "Description": "Moochie presents a women's sparkling soothing blue color jutti perfect for all occasions. Heavily embellished with mirror work, this gorgeous pair is sure to enhance your day and outfit. Elevate your look with these gorgeous pair, guaranteed to brighten up your day and outfit. Step into elegance with Moochie Women's Jutti and make a statement wherever you go.",
        "Specifications": {
            "Style": "Pumps",
            "Features": [
                "Crafted from high quality textile material.",
                "Heavily embellished with mirror work.",
                "Leather sole of the jutti provides comfort and durability.",
                "Features a closed-toe design with a rounded or slightly pointed toe box."
            ],
            "Materials": [
                "Upper: Textile",
                "Sole: Leather"
            ]
        },
        "Company": "Apex",
        "Category": "Jutti",
        "Gender": "Female"
    },
    {
        "Name": "Moochie Women's Jutti",
        "Price": "Tk 2,990",
        "Image_links": [
            "https://storage.apex4u.com/61588A48_3.jpeg",
            "https://storage.apex4u.com/61588A48_1.jpeg",
            "https://storage.apex4u.com/61588A48_4.jpeg",
            "https://storage.apex4u.com/61588A48_2.jpeg"
        ],
        "Link": "https://www.apex4u.com/product/moochie-womens-jutti-61588a48",
        "Description": "Moochie Women's Jutti brings a touch of elegance to your ensemble. These exotic white juttis are adorned with intricate mirror work, adding a hint of glamour to any outfit. Crafted from premium textile material, they offer both style and comfort. These juttis are ideal for every occasion and will definitely add some color and flair to your outfit. With Moochie Women's Jutti, you can easily boost your style and exude refinement.",
        "Specifications": {
            "Style": "Pumps",
            "Features": [
                "Crafted from high quality textile material.",
                "Heavily embellished with mirror work.",
                "Leather sole of the jutti provides comfort and durability.",
                "Features a closed-toe design with a rounded or slightly pointed toe box."
            ],
            "Materials": [
                "Upper: Textile",
                "Sole: Leather"
            ]
        },
        "Company": "Apex",
        "Category": "Jutti",
        "Gender": "Female"
    },
    {
        "Name": "Moochie Women's Jutti",
        "Price": "Tk 2,990",
        "Image_links": [
            "https://storage.apex4u.com/61578A52_4.jpeg",
            "https://storage.apex4u.com/61578A52_2.jpeg",
            "https://storage.apex4u.com/61578A52_3.jpeg",
            "https://storage.apex4u.com/61578A52_1.jpeg"
        ],
        "Link": "https://www.apex4u.com/product/moochie-womens-gold-pearls-jutti-61578a52",
        "Description": "Moochie presents shiny sparkling women's jutti perfect for all occasions. Heavily embellished with gold color beads and ivory pearls to create a striking print. These stunning shoes will definitely make your day and wardrobe more cheerful. Upgrade your style with them. Wear Moochie Women's Jutti to exude elegance and turn heads everywhere you go.",
        "Specifications": {
            "Style": "Pumps",
            "Features": [
                "Golden shade adds a touch of elegance and luxury.",
                "Crafted from high quality textile material.",
                "Leather sole of the jutti provides comfort and durability.",
                "Close-toe shoe that features a rounded toe box."
            ],
            "Materials": [
                "Upper: Textile",
                "Sole: Leather"
            ]
        },
        "Company": "Apex",
        "Category": "Jutti",
        "Gender": "Female"
    },
    {
        "Name": "Moochie Women's Jutti",
        "Price": "Tk 2,990",
        "Image_links": [
            "https://storage.apex4u.com/61578A49_3.jpeg",
            "https://storage.apex4u.com/61578A49_4.jpeg",
            "https://storage.apex4u.com/61578A49_2.jpeg",
            "https://storage.apex4u.com/61578A49_1.jpeg"
        ],
        "Link": "https://www.apex4u.com/product/moochie-womens-bright-sunny-jutti-61578a49",
        "Description": "Moochie presents a women's sparkling bright sunny yellow color jutti perfect for all occasions. Heavily embellished with mirror work, this gorgeous pair is sure to enhance your day and outfit. Elevate your look with these gorgeous pair, guaranteed to brighten up your day and outfit. Step into elegance with Moochie Women's Jutti and make a statement wherever you go.",
        "Specifications": {
            "Style": "Pumps",
            "Features": [
                "Crafted from high quality textile material.",
                "Heavily embellished with mirror work.",
                "Leather sole of the jutti provides comfort and durability.",
                "Features a closed-toe design with a rounded or slightly pointed toe box."
            ],
            "Materials": [
                "Upper: Textile",
                "Sole: Leather"
            ]
        },
        "Company": "Apex",
        "Category": "Jutti",
        "Gender": "Female"
    },
    {
        "Name": "Moochie Women's Jutti",
        "Price": "Tk 2,990",
        "Image_links": [
            "https://storage.apex4u.com/61568A53_1.jpeg",
            "https://storage.apex4u.com/61568A53_4.jpeg",
            "https://storage.apex4u.com/61568A53_3.jpeg",
            "https://storage.apex4u.com/61568A53_2.jpeg"
        ],
        "Link": "https://www.apex4u.com/product/moochie-womens-pearls-jutti-61568a53",
        "Description": "Elevate your ethnic chic with Moochie Women's Jutti, an exquisite blend of tradition and trend. Crafted with precision, these juttis boast intricate detailing and fine craftsmanship. Slip into comfort and style with the soft, leather construction and a design that seamlessly fuses cultural charm with contemporary flair. Moochie Women's Jutti is more than footwear; it's a celebration of heritage and fashion, ensuring each step tells a story of elegance and cultural richness.",
        "Specifications": {
            "Style": "Pumps",
            "Features": [
                "Gold-colored zardosi embroidered work.",
                "Crafted from high quality textile material.",
                "Sole provides comfort, flexibility, and durability.",
                "Gold embroidery provides a touch of elegance and precise craftsmanship."
            ],
            "Materials": [
                "Upper: Textile",
                "Sole: Leather"
            ]
        },
        "Company": "Apex",
        "Category": "Jutti",
        "Gender": "Female"
    },
    {
        "Name": "Moochie Women's Jutti",
        "Price": "Tk 2,990",
        "Image_links": [
            "https://storage.apex4u.com/61558A51_2.jpeg",
            "https://storage.apex4u.com/61558A51_1.jpeg",
            "https://storage.apex4u.com/61558A51_4.jpeg",
            "https://storage.apex4u.com/61558A51_3.jpeg"
        ],
        "Link": "https://www.apex4u.com/product/moochie-womens-roseate-jutti-61558a51",
        "Description": "Introducing Moochie Women's Jutti, a dazzling addition to your footwear collection. Perfect for all occasions, these exotic pink juttis are heavily embellished with mirror work, adding a touch of sparkle to your day and outfit. Crafted from high-quality textile material, they offer both style and comfort. Step into elegance and elevate your look with Moochie Women's Jutti, guaranteed to brighten up any ensemble.",
        "Specifications": {
            "Style": "Pumps",
            "Features": [
                "Designed to provide a comfortable fit.",
                "Crafted from high quality textile material.",
                "Heavily embellished with light pink beads.",
                "Trendy an stylish."
            ],
            "Materials": [
                "Upper: Textile",
                "Sole: Leather"
            ]
        },
        "Company": "Apex",
        "Category": "Jutti",
        "Gender": "Female"
    },
    {
        "Name": "Moochie Women's Jutti",
        "Price": "Tk 2,990",
        "Image_links": [
            "https://storage.apex4u.com/61558A50_2.jpeg",
            "https://storage.apex4u.com/61558A50_4.jpeg",
            "https://storage.apex4u.com/61558A50_3.jpeg",
            "https://storage.apex4u.com/61558A50_1.jpeg"
        ],
        "Link": "https://www.apex4u.com/product/moochie-womens-magenta-beads-jutti-61558a50",
        "Description": "Elevate your ethnic chic with Moochie Women's Jutti, an exquisite blend of tradition and trend. Crafted with precision, these juttis boast intricate detailing and fine craftsmanship. Slip into comfort and style with the soft, leather construction and a design that seamlessly fuses cultural charm with contemporary flair. Moochie Women's Jutti is more than footwear; it's a celebration of heritage and fashion, ensuring each step tells a story of elegance and cultural richness.",
        "Specifications": {
            "Style": "Pumps",
            "Features": [
                "Designed to provide a stylish and comfortable fit.",
                "Crafted from high quality textile material.",
                "Embellished with beautiful and detailed beadwork.",
                "Close-toe shoe that features a rounded toe box."
            ],
            "Materials": [
                "Upper: Textile",
                "Sole: Leather"
            ]
        },
        "Company": "Apex",
        "Category": "Jutti",
        "Gender": "Female"
    }
]